setup.py
weathercheck/__init__.py
weathercheck/weathercheck.py
weathercheck.egg-info/PKG-INFO
weathercheck.egg-info/SOURCES.txt
weathercheck.egg-info/dependency_links.txt
weathercheck.egg-info/requires.txt
weathercheck.egg-info/top_level.txt