Metadata-Version: 2.1
Name: weathercheck
Version: 1.0.0
Summary: Weather forecast data
Home-page: https://github.com/oreroko/weathercheck
Author: Gabriel Szollosy
Author-email: mathohota@gmail.com
License: MIT
Keywords: weather,openweather,forecast
Platform: UNKNOWN
Classifier: Development Status :: 3 - Alpha
Classifier: Intended Audience :: Developers
Classifier: Topic :: Software Development :: Build Tools
Classifier: License :: OSI Approved :: MIT License
Classifier: Programming Language :: Python :: 3.5
Classifier: Programming Language :: Python :: 3.6
Classifier: Programming Language :: Python :: 3.7
Classifier: Programming Language :: Python :: 3.8
Classifier: Programming Language :: Python :: 3.9
